mathics/__init__.py
mathics/__main__.py
mathics/benchmark.py
mathics/docpipeline.py
mathics/interrupt.py
mathics/interupt.py
mathics/profile_mathics.py
mathics/session.py
mathics/settings.py
mathics/system_info.py
mathics/timing.py
mathics/version.py
mathics/Packages/BoolEval/BoolEval.m
mathics/Packages/BoolEval/PacletInfo.m
mathics/Packages/BoolEval/Kernel/init.m
mathics/Packages/Chemistry/Resources/RDKitData/Data/DTDs/validate.py
mathics/Packages/Chemistry/Resources/RDKitData/Data/Pains/test_data/run_tests.py
mathics/Packages/Chemistry/Resources/RDKitData/Data/SmartsLib/tests/bench2.py
mathics/Packages/Combinatorica/CombinatoricaV06.m
mathics/Packages/Combinatorica/CombinatoricaV091.m
mathics/Packages/Combinatorica/CombinatoricaV201.m
mathics/Packages/Combinatorica/Kernel/init.m
mathics/Packages/Combinatorica-repo/setup.py
mathics/Packages/Combinatorica-repo/test/__init__.py
mathics/Packages/Combinatorica-repo/test/helper.py
mathics/Packages/Combinatorica-repo/test/test_combinatorica_v091.py
mathics/Packages/Combinatorica-repo/test/test_combinatorica_v201.py
mathics/Packages/DiscreteMath/CombinatoricaV06.m
mathics/Packages/DiscreteMath/CombinatoricaV091.m
mathics/Packages/DiscreteMath/CombinatoricaV201.m
mathics/Packages/DiscreteMath/RSolve.m
mathics/Packages/DiscreteMath/Kernel/init.m
mathics/Packages/Kernel/init.m
mathics/Packages/MUnit/MUnitLoader.m
mathics/Packages/MUnit/PacletInfo.m
mathics/Packages/MUnit-save/PacletInfo.m
mathics/Packages/Miscellaneous/Calendar-orig.m
mathics/Packages/Miscellaneous/Calendar.m
mathics/Packages/Miscellaneous/Music-orig.m
mathics/Packages/Miscellaneous/Music.m
mathics/Packages/Miscellaneous/PhysicalConstants-orig.m
mathics/Packages/Miscellaneous/PhysicalConstants.m
mathics/Packages/Miscellaneous/Kernel/init.m
mathics/Packages/Rubi/IntegrationUtilityFunctions.m
mathics/Packages/Rubi/PacletInfo.m
mathics/Packages/Rubi/Rubi.m
mathics/Packages/Rubi/ShowStepFormatting.m
mathics/Packages/Rubi/ShowStepRoutines.m
mathics3-9.0.0.dist-info/licenses/AUTHORS.txt
mathics3-9.0.0.dist-info/licenses/COPYING.txt
mathics3-9.0.0.dist-info/METADATA
mathics3-9.0.0.dist-info/WHEEL
mathics3-9.0.0.dist-info/entry_points.txt
mathics3-9.0.0.dist-info/top_level.txt
mathics3-9.0.0.dist-info/RECORD
