Metadata-Version: 2.4
Name: Mathics3
Version: 9.0.0
Summary: A general-purpose computer algebra system.
Maintainer-email: Mathics Group <mathics-devel@googlegroups.com>
License-Expression: GPL-3.0-or-later
Project-URL: Homepage, https://mathics.org/
Project-URL: Downloads, https://github.com/Mathics3/mathics-core/releases
Keywords: Mathematica,Wolfram,Interpreter,Shell,Math,CAS
Classifier: Intended Audience :: Developers
Classifier: Intended Audience :: Science/Research
Classifier: Programming Language :: Python
Classifier: Programming Language :: Python :: 3.10
Classifier: Programming Language :: Python :: 3.11
Classifier: Programming Language :: Python :: 3.12
Classifier: Programming Language :: Python :: 3.13
Classifier: Programming Language :: Python :: Implementation :: CPython
Classifier: Programming Language :: Python :: Implementation :: PyPy
Classifier: Topic :: Scientific/Engineering
Classifier: Topic :: Scientific/Engineering :: Mathematics
Classifier: Topic :: Scientific/Engineering :: Physics
Classifier: Topic :: Software Development :: Interpreters
Requires-Python: >=3.10
License-File: COPYING.txt
License-File: AUTHORS.txt
Requires-Dist: Mathics-Scanner>1.4.1
Requires-Dist: mpmath>=1.2.0
Requires-Dist: numpy
Requires-Dist: palettable
Requires-Dist: pillow>=9.2
Requires-Dist: pint
Requires-Dist: python-dateutil
Requires-Dist: Pympler
Requires-Dist: requests
Requires-Dist: scipy
Requires-Dist: setuptools
Requires-Dist: stopit; platform_system != "Emscripten"
Requires-Dist: sympy<1.14,>=1.13
Provides-Extra: dev
Requires-Dist: pexpect; extra == "dev"
Requires-Dist: pytest; extra == "dev"
Provides-Extra: full
Requires-Dist: ipywidgets; extra == "full"
Requires-Dist: llvmlite; extra == "full"
Requires-Dist: lxml; extra == "full"
Requires-Dist: psutil; extra == "full"
Requires-Dist: pyocr; extra == "full"
Requires-Dist: scikit-image>=0.17; extra == "full"
Requires-Dist: unidecode; extra == "full"
Requires-Dist: wordcloud>=1.9.3; extra == "full"
Provides-Extra: cython
Requires-Dist: cython; extra == "cython"
Dynamic: license-file
